.gitignore
.travis.yml
LICENSE
README.rst
example.png
logo-300px.png
logo-600px.png
logo.svg
setup.py
vegascope.py
vegascope.egg-info/PKG-INFO
vegascope.egg-info/SOURCES.txt
vegascope.egg-info/dependency_links.txt
vegascope.egg-info/entry_points.txt
vegascope.egg-info/top_level.txt